PhageBoost/__init__.py
PhageBoost/bbcache.py
PhageBoost/calc_features.py
PhageBoost/get_genecalls.py
PhageBoost/get_matches.py
PhageBoost/get_predictions.py
PhageBoost/main.py
PhageBoost/models/model_delta_std_hacked.pickled.silent.gz
example/data/NC_000907.fasta.gz
PhageBoost-0.1.7.dist-info/LICENSE
PhageBoost-0.1.7.dist-info/METADATA
PhageBoost-0.1.7.dist-info/WHEEL
PhageBoost-0.1.7.dist-info/entry_points.txt
PhageBoost-0.1.7.dist-info/top_level.txt
PhageBoost-0.1.7.dist-info/RECORD
