Metadata-Version: 2.1
Name: PhageBoost
Version: 0.1.7
Summary: a Fast Prophage and Phage Predictor
Home-page: https://github.com/ku-cbd/PhageBoost
Author: Kimmo Sirén and Thomas Sicheritz-Pontén
Author-email: kkpsiren@gmail.com
License: UNKNOWN
Keywords: machine learning,bioinformatics,phage,prophage,bacteria,ngs,metagenomics,wgs,microbiology
Platform: UNKNOWN
Classifier: Programming Language :: Python :: 3
Classifier: License :: OSI Approved :: MIT License
Classifier: Operating System :: OS Independent
Classifier: Intended Audience :: Science/Research
Classifier: Development Status :: 3 - Alpha 
Classifier: Topic :: Scientific/Engineering
Requires-Python: >=3.6
Requires-Dist: biopython
Requires-Dist: joblib
Requires-Dist: more-itertools
Requires-Dist: numpy
Requires-Dist: pandas
Requires-Dist: pickleshare
Requires-Dist: pyrodigal
Requires-Dist: scipy
Requires-Dist: tables
Requires-Dist: xgboost
Requires-Dist: cachier
Requires-Dist: tabulate
